README.md
setup.py
iRep/__init__.py
iRep/bPTR
iRep/gc_skew.py
iRep/iRep
iRep/iRep_filter.py
iRep.egg-info/PKG-INFO
iRep.egg-info/SOURCES.txt
iRep.egg-info/dependency_links.txt
iRep.egg-info/requires.txt
iRep.egg-info/top_level.txt
test/test_suite.py