Metadata-Version: 1.1
Name: iRep
Version: 1.1.14
Summary: calculate iRep replication rates from metagenome sequencing
Home-page: https://github.com/christophertbrown/iRep
Author: Chris Brown
Author-email: ctb@berkeley.edu
License: MIT
Platform: UNKNOWN
Classifier: Programming Language :: Python
Classifier: Programming Language :: Python :: 3
